__init__.py
mqss/__init__.py
mqss/pennylane_adapter/__init__.py
mqss/pennylane_adapter/adapter.py
mqss/pennylane_adapter/backend.py
mqss/pennylane_adapter/config.py
mqss/pennylane_adapter/device.py
mqss/pennylane_adapter/job.py
mqss/pennylane_adapter/mqss_resources.py
mqss/pennylane_adapter/utils.py
mqss_pennylane_adapter-1.1.2.dist-info/METADATA
mqss_pennylane_adapter-1.1.2.dist-info/WHEEL
mqss_pennylane_adapter-1.1.2.dist-info/top_level.txt
mqss_pennylane_adapter-1.1.2.dist-info/RECORD
