Metadata-Version: 2.4
Name: mqss-pennylane-adapter
Version: 1.1.2
Summary: A Pennylane Adapter package for the Munich Quantum Software Stack.
Author-email: Burak <burak.mete@lrz.de>
Requires-Python: >=3.11
Requires-Dist: pennylane>=0.39.0
Requires-Dist: python-dotenv>=1.0.1
Requires-Dist: qiskit<1.4.0,>=1.2.4
Requires-Dist: requests>=2.32.3
Requires-Dist: mqp-client==0.1.4
Requires-Dist: mqss-client>=0.2.0
